har2case2/__about__.py
har2case2/__init__.py
har2case2/cli.py
har2case2/compat.py
har2case2/core.py
har2case2/utils.py
tests/__init__.py
tests/test_har.py
tests/test_utils.py
har2case2-0.3.2.dist-info/LICENSE
har2case2-0.3.2.dist-info/METADATA
har2case2-0.3.2.dist-info/WHEEL
har2case2-0.3.2.dist-info/entry_points.txt
har2case2-0.3.2.dist-info/top_level.txt
har2case2-0.3.2.dist-info/RECORD
