Metadata-Version: 2.1
Name: har2case2
Version: 0.3.2
Summary: fork from https://github.com/HttpRunner/har2case. Convert HAR(HTTP Archive) to YAML/JSON testcases for HttpRunner.
Home-page: https://github.com/alienwow/har2case
Author: Vito
Author-email: wuwenhao0327@gmail.com
License: Apache-2.0
Keywords: har converter HttpRunner yaml json
Platform: UNKNOWN
Classifier: Development Status :: 3 - Alpha
Classifier: License :: OSI Approved :: Apache Software License
Classifier: Programming Language :: Python
Classifier: Programming Language :: Python :: 2
Classifier: Programming Language :: Python :: 2.7
Classifier: Programming Language :: Python :: 3
Classifier: Programming Language :: Python :: 3.4
Classifier: Programming Language :: Python :: 3.5
Classifier: Programming Language :: Python :: 3.6
Classifier: Programming Language :: Python :: 3.7
Requires-Python: >=2.7, !=3.0.*, !=3.1.*, !=3.2.*, !=3.3.*, <4
Requires-Dist: PyYAML
